ejemploProyecto/calculo.py
ejemploProyecto/constantes.py
ppiedrachinchilla-0.0.1.dist-info/METADATA
ppiedrachinchilla-0.0.1.dist-info/WHEEL
ppiedrachinchilla-0.0.1.dist-info/licenses/LICENSE
ppiedrachinchilla-0.0.1.dist-info/RECORD
