Metadata-Version: 2.1
Name: ppiedrachinchilla
Version: 0.0.1
Summary: Ejemplo de como crear un paquete
Project-URL: Homepage, https://github.com/piedrachin/Investigacion_Progra2.git
Project-URL: Bug Tracker, https://github.com/piedrachin/Investigacion_Progra2.git/issues
Author-email: xxx <xxx@gmail.com>
License: MIT License
License-File: LICENSE
Classifier: License :: OSI Approved :: MIT License
Classifier: Operating System :: OS Independent
Classifier: Programming Language :: Python :: 3
Requires-Python: >=3.11
